pyblingapi/__init__.py
pyblingapi/errors.py
pyblingapi/servidor.py
pyblingapi/tools.py
pyblingapi/templates/categoria.xml
pyblingapi/templates/categoriasLoja.xml
pyblingapi/templates/contapagar.xml
pyblingapi/templates/contareceber.xml
pyblingapi/templates/contato.xml
pyblingapi/templates/contatos.xml
pyblingapi/templates/contrato.xml
pyblingapi/templates/deposito.xml
pyblingapi/templates/depositos.xml
pyblingapi/templates/formapagamento.xml
pyblingapi/templates/logistica.xml
pyblingapi/templates/nfce.xml
pyblingapi/templates/nfe.xml
pyblingapi/templates/nfse.xml
pyblingapi/templates/notafiscal.xml
pyblingapi/templates/ordemproducao.xml
pyblingapi/templates/pedido.xml
pyblingapi/templates/produto.xml
pyblingapi/templates/rastreamento_evento.xml
pyblingapi/templates/rastreamento_vincula.xml
pyblingapi/templates/rastreamentoevento.xml
pyblingapi/templates/rastreamentovincular.xml
pyblingapi/xml/__init__.py
pyblingapi/xml/filters.py
PyBlingAPI-0.0.1.dist-info/METADATA
PyBlingAPI-0.0.1.dist-info/WHEEL
PyBlingAPI-0.0.1.dist-info/top_level.txt
PyBlingAPI-0.0.1.dist-info/RECORD
