Metadata-Version: 2.1
Name: PyBlingAPI
Version: 0.0.1
Summary: PyBlingAPI é uma biblioteca para troca de dados com o Bling ERP
Home-page: https://gitlab.com/Defendi/pyblingapi
Author: Alexandre Defendi
Author-email: alexandre_defendi@hotmail.com
License: LGPL-v2.1+
Keywords: Bling
Platform: UNKNOWN
Classifier: Development Status :: 5 - Production/Stable
Classifier: Environment :: Plugins
Classifier: Intended Audience :: Developers
Classifier: License :: OSI Approved :: GNU Lesser General Public License v2 or later (LGPLv2+)
Classifier: Operating System :: OS Independent
Classifier: Programming Language :: Python
Classifier: Programming Language :: Python :: 3.7
Classifier: Programming Language :: Python :: 3.6
Classifier: Programming Language :: Python :: 3.5
Classifier: Programming Language :: Python :: 3.4
Classifier: Topic :: Software Development :: Libraries :: Python Modules
Requires-Dist: requests (==2.23.0)
Requires-Dist: Jinja2 (>=2.8)
Requires-Dist: lxml (<5,>=3.5.0)
